example_package_TEST_ABI_SDK/__init__.py
example_package_TEST_ABI_SDK/config/__init__.py
example_package_TEST_ABI_SDK/config/constants.py
example_package_TEST_ABI_SDK/db/__init__.py
example_package_TEST_ABI_SDK/db/sqlalchemy_connector.py
example_package_TEST_ABI_SDK/exceptions/__init__.py
example_package_TEST_ABI_SDK/exceptions/base_exceptions.py
example_package_TEST_ABI_SDK/sfdc/__init__.py
example_package_TEST_ABI_SDK/sfdc/sfdc_consumer.py
example_package_test_abi_sdk-0.1.0.dist-info/METADATA
example_package_test_abi_sdk-0.1.0.dist-info/WHEEL
example_package_test_abi_sdk-0.1.0.dist-info/top_level.txt
example_package_test_abi_sdk-0.1.0.dist-info/RECORD
