Metadata-Version: 2.4
Name: example_package_TEST_ABI_SDK
Version: 0.1.0
Summary: Django REST Framework authentication middleware
Author: test
Author-email: 
Requires-Python: >=3.6
Requires-Dist: SQLAlchemy==2.0.36
Requires-Dist: requests==2.32.4
Requires-Dist: Logbook==1.8.2
Dynamic: author
Dynamic: description
Dynamic: description-content-type
Dynamic: requires-dist
Dynamic: requires-python
Dynamic: summary
